package/__init__.py
package/calculate_area.py
package/calculate_rf.py
package/to_excel.py
package/visualize.py
rf_hypersonic_emissions-2.0.dist-info/licenses/LICENSE
rf_hypersonic_emissions-2.0.dist-info/METADATA
rf_hypersonic_emissions-2.0.dist-info/WHEEL
rf_hypersonic_emissions-2.0.dist-info/top_level.txt
rf_hypersonic_emissions-2.0.dist-info/RECORD
