Metadata-Version: 2.4
Name: rf_hypersonic_emissions
Version: 2.0
Summary: Calculate the radiative forcing of hypersonic aircraft trajectories.
Project-URL: Homepage, https://github.com/johannespletzer/rf-of-hypersonic-aircraft-emissions
Project-URL: Repository, https://github.com/johannespletzer/rf-of-hypersonic-aircraft-emissions.git
Requires-Python: >=3.7
License-File: LICENSE
Requires-Dist: numpy
Requires-Dist: pandas
Requires-Dist: xarray
Requires-Dist: scipy
Requires-Dist: xlsxwriter
Requires-Dist: netcdf4
Requires-Dist: aerocalc3
Dynamic: license-file
